{
    "backend": "flask",
    "db_name": "",
    "db_pass": "",
    "db_type": "sqlite",
    "db_user": "",
    "dbms": "1",
    "description": "generated product",
    "design": "datta-able",
    "docker": "1",
    "err_code": 0,
    "frontend": "",
    "heroku": "0",
    "pattern": "mvc",
    "pro": "0",
    "task_id": "bf594801-e1c9-40dd-a09e-95783a27fb8f",
    "task_info": "Upload Sources [0%] - 148 files",
    "task_output": "bf594801-e1c9-40dd-a09e-95783a27fb8f.zip",
    "task_result": "SUCCESS",
    "task_state": "RUNNING",
    "task_ts_end": "2024-02-28-18-11-06",
    "task_ts_start": "2024-02-28-18-11-04"
}